{
  "preferences": {
    "https://sh.zu.anjuke.com/fangyuan/4524763489573898": {
      "area_m2": "72.5",
      "community": "海尚康庭",
      "layout": "2室1厅",
      "platform": "安居客",
      "pref": "dislike",
      "rank": 37,
      "rent": 3800,
      "title": "电梯大2房，空置，随时入住",
      "updated_at": "2026-07-01T13:24:51+00:00",
      "url": "https://sh.zu.anjuke.com/fangyuan/4524763489573898"
    },
    "https://sh.zu.anjuke.com/fangyuan/4528846731090951": {
      "area_m2": "60.2",
      "community": "秀怡苑",
      "layout": "2室1厅",
      "platform": "安居客",
      "pref": "like",
      "rank": 18,
      "rent": 3850,
      "title": "实拍 秀沿路双南两房一厅 民水民电 燃气厨房 采光好",
      "updated_at": "2026-07-01T13:20:49+00:00",
      "url": "https://sh.zu.anjuke.com/fangyuan/4528846731090951"
    },
    "https://sh.zu.anjuke.com/fangyuan/4535115755400200": {
      "area_m2": "39",
      "community": "沪南路2420号楼",
      "layout": "1室1厅",
      "platform": "安居客",
      "pref": "dislike",
      "rank": 26,
      "rent": 2500,
      "title": "首月5折 直达东体地铁口 民用水电精装修24小时安保随时住",
      "updated_at": "2026-07-01T13:23:40+00:00",
      "url": "https://sh.zu.anjuke.com/fangyuan/4535115755400200"
    },
    "https://sh.zu.anjuke.com/fangyuan/4546287338155014": {
      "area_m2": "72.3",
      "community": "康桥月苑(南区)",
      "layout": "2室1厅",
      "platform": "安居客",
      "pref": "dislike",
      "rank": 35,
      "rent": 3700,
      "title": "原业主出租，南北通透。有钥匙",
      "updated_at": "2026-07-01T13:24:30+00:00",
      "url": "https://sh.zu.anjuke.com/fangyuan/4546287338155014"
    },
    "https://sh.zu.anjuke.com/fangyuan/4569840130989058": {
      "area_m2": "57.2",
      "community": "川杨新苑(三期)",
      "layout": "2室1厅",
      "platform": "安居客",
      "pref": "dislike",
      "rank": 7,
      "rent": 4000,
      "title": "川杨新苑三期2室一厅一楼带院子",
      "updated_at": "2026-07-01T13:20:49+00:00",
      "url": "https://sh.zu.anjuke.com/fangyuan/4569840130989058"
    },
    "https://sh.zu.anjuke.com/fangyuan/4571326658567178": {
      "area_m2": "75.6",
      "community": "海尚康庭",
      "layout": "2室1厅",
      "platform": "安居客",
      "pref": "dislike",
      "rank": 36,
      "rent": 3800,
      "title": "海尚康庭 2室1厅1卫 拎包入住 南北通透，近地铁11号线",
      "updated_at": "2026-07-01T13:24:42+00:00",
      "url": "https://sh.zu.anjuke.com/fangyuan/4571326658567178"
    },
    "https://sh.zu.anjuke.com/fangyuan/4579899244307460": {
      "area_m2": "78.5",
      "community": "秀康新城达城家园",
      "layout": "2室2厅",
      "platform": "安居客",
      "pref": "dislike",
      "rank": 42,
      "rent": 3800,
      "title": "商品房电梯南北通大两房 可长租办居住证 崂山旁",
      "updated_at": "2026-07-01T13:25:23+00:00",
      "url": "https://sh.zu.anjuke.com/fangyuan/4579899244307460"
    },
    "https://sh.zu.anjuke.com/fangyuan/4586711030717450": {
      "area_m2": "30",
      "community": "港城中环汇领寓",
      "layout": "1室0厅",
      "platform": "安居客",
      "pref": "dislike",
      "rank": 11,
      "rent": 2480,
      "title": "我是管家，无中阶肺，自己住在里面，大力推荐好房子，宠物友好",
      "updated_at": "2026-07-01T13:20:49+00:00",
      "url": "https://sh.zu.anjuke.com/fangyuan/4586711030717450"
    },
    "https://sh.zu.anjuke.com/fangyuan/4588121846440961": {
      "area_m2": "78.5",
      "community": "秀康新城达城家园",
      "layout": "2室1厅",
      "platform": "安居客",
      "pref": "dislike",
      "rank": 43,
      "rent": 3800,
      "title": "新上 电梯南北两房 可长租 可办居住证 看房随时",
      "updated_at": "2026-07-01T13:25:28+00:00",
      "url": "https://sh.zu.anjuke.com/fangyuan/4588121846440961"
    },
    "https://sh.zu.anjuke.com/fangyuan/4603627989015566": {
      "area_m2": "78.7",
      "community": "康桥月苑(北区)",
      "layout": "2室1厅",
      "platform": "安居客",
      "pref": "dislike",
      "rank": 44,
      "rent": 4000,
      "title": "近11号线秀沿路站 康桥漕河泾 精装两房 业主出租",
      "updated_at": "2026-07-01T13:25:36+00:00",
      "url": "https://sh.zu.anjuke.com/fangyuan/4603627989015566"
    },
    "https://sh.zu.anjuke.com/fangyuan/4603902265549834": {
      "area_m2": "45",
      "community": "紫薇路372号楼",
      "layout": "1室1厅",
      "platform": "安居客",
      "pref": "dislike",
      "rank": 8,
      "rent": 3000,
      "title": "整租一室一厅带院子，可办居住证，押一付一，全落地窗！",
      "updated_at": "2026-07-01T13:20:49+00:00",
      "url": "https://sh.zu.anjuke.com/fangyuan/4603902265549834"
    },
    "https://sh.zu.anjuke.com/fangyuan/4604379326096387": {
      "area_m2": "38",
      "community": "沪南路2420号楼",
      "layout": "1室1厅",
      "platform": "安居客",
      "pref": "dislike",
      "rank": 28,
      "rent": 2500,
      "title": "18号线 御桥 家电齐全 押一付一 拎包入住",
      "updated_at": "2026-07-01T13:23:49+00:00",
      "url": "https://sh.zu.anjuke.com/fangyuan/4604379326096387"
    },
    "https://sh.zu.anjuke.com/fangyuan/4605431038155781": {
      "area_m2": "90.6",
      "community": "汇腾东苑",
      "layout": "2室2厅",
      "platform": "安居客",
      "pref": "like",
      "rank": 25,
      "rent": 3500,
      "title": "汇腾东苑精装全配拎包入住两房两厅一卫 沈梅路站旁",
      "updated_at": "2026-07-01T13:23:34+00:00",
      "url": "https://sh.zu.anjuke.com/fangyuan/4605431038155781"
    },
    "https://sh.zu.anjuke.com/fangyuan/4606745891658753": {
      "area_m2": "118",
      "community": "古桐四村",
      "layout": "1室1厅",
      "platform": "安居客",
      "pref": "like",
      "rank": 2,
      "rent": 2800,
      "title": "金科路旁 独立一室一厅 近软件园 药谷等 生活便利 拎包入住",
      "updated_at": "2026-07-01T13:20:49+00:00",
      "url": "https://sh.zu.anjuke.com/fangyuan/4606745891658753"
    },
    "https://sh.zu.anjuke.com/fangyuan/4624795680037902": {
      "area_m2": "60.1",
      "community": "汤巷雅苑",
      "layout": "2室1厅",
      "platform": "安居客",
      "pref": "dislike",
      "rank": 19,
      "rent": 3650,
      "title": "近漕河泾 商务绿洲 精装修两房 可整租可分租 免租期15天",
      "updated_at": "2026-07-01T13:21:27+00:00",
      "url": "https://sh.zu.anjuke.com/fangyuan/4624795680037902"
    },
    "https://sh.zu.anjuke.com/fangyuan/4626699735919627": {
      "area_m2": "35",
      "community": "横沔江路86号楼",
      "layout": "1室1厅",
      "platform": "安居客",
      "pref": "dislike",
      "rank": 5,
      "rent": 2100,
      "title": "张江租房近双子塔，独立厨卫押一付一",
      "updated_at": "2026-07-01T13:20:49+00:00",
      "url": "https://sh.zu.anjuke.com/fangyuan/4626699735919627"
    },
    "https://sh.zu.anjuke.com/fangyuan/4629550252682247": {
      "area_m2": "112.5",
      "community": "宁怡苑",
      "layout": "1室1厅",
      "platform": "安居客",
      "pref": "like",
      "rank": 3,
      "rent": 3000,
      "title": "11号线康新公路地铁站附近有漕河泾商务绿洲吉祥航空新月湾总部",
      "updated_at": "2026-07-01T13:20:49+00:00",
      "url": "https://sh.zu.anjuke.com/fangyuan/4629550252682247"
    },
    "https://sh.zu.anjuke.com/fangyuan/4630751525121032": {
      "area_m2": "40",
      "community": "萃宸璟庭",
      "layout": "1室0厅",
      "platform": "安居客",
      "pref": "dislike",
      "rank": 34,
      "rent": 2800,
      "title": "1318莲溪路地铁站萃宸璟庭朝南燃气做饭干湿分离可办车位",
      "updated_at": "2026-07-01T13:24:21+00:00",
      "url": "https://sh.zu.anjuke.com/fangyuan/4630751525121032"
    },
    "https://sh.zu.anjuke.com/fangyuan/4634839696647172": {
      "area_m2": "93.5",
      "community": "颐谷南苑",
      "layout": "2室1厅",
      "platform": "安居客",
      "pref": "dislike",
      "rank": 24,
      "rent": 3800,
      "title": "实房拍摄 颐谷北苑两房两卫出租 民用水电 出行便利 随时看",
      "updated_at": "2026-07-01T13:22:30+00:00",
      "url": "https://sh.zu.anjuke.com/fangyuan/4634839696647172"
    },
    "https://sh.zu.anjuke.com/fangyuan/4635219580510220": {
      "area_m2": "60",
      "community": "东康名苑",
      "layout": "2室1厅",
      "platform": "安居客",
      "pref": "dislike",
      "rank": 41,
      "rent": 4000,
      "title": "电梯朝南小两房I适合同事闺蜜合租或三口小家庭I经济实惠",
      "updated_at": "2026-07-01T13:25:12+00:00",
      "url": "https://sh.zu.anjuke.com/fangyuan/4635219580510220"
    },
    "https://sh.zu.anjuke.com/fangyuan/4636507042290695": {
      "area_m2": "50",
      "community": "芳华路63号小区",
      "layout": "1室1厅",
      "platform": "安居客",
      "pref": "dislike",
      "rank": 6,
      "rent": 3000,
      "title": "芳华路地铁口 精装修民用水电押一付一 拎包入住",
      "updated_at": "2026-07-01T13:20:49+00:00",
      "url": "https://sh.zu.anjuke.com/fangyuan/4636507042290695"
    },
    "https://sh.zu.anjuke.com/fangyuan/4636620263022595": {
      "area_m2": "30",
      "community": "川周公路2788弄小区",
      "layout": "1室0厅",
      "platform": "安居客",
      "pref": "dislike",
      "rank": 15,
      "rent": 2500,
      "title": "环境优美精致装修拎包入住押一付一",
      "updated_at": "2026-07-01T13:20:49+00:00",
      "url": "https://sh.zu.anjuke.com/fangyuan/4636620263022595"
    },
    "https://sh.zu.anjuke.com/fangyuan/4636630898564109": {
      "area_m2": "25",
      "community": "芳华路63号小区",
      "layout": "1室1厅",
      "platform": "安居客",
      "pref": "dislike",
      "rank": 29,
      "rent": 2800,
      "title": "拎包即住精装整租一居 独立厨卫 近地铁商超 民水民电可月",
      "updated_at": "2026-07-01T13:23:57+00:00",
      "url": "https://sh.zu.anjuke.com/fangyuan/4636630898564109"
    },
    "https://sh.zu.anjuke.com/fangyuan/4636637714015242": {
      "area_m2": "32",
      "community": "川周公路2788弄小区",
      "layout": "1室1厅",
      "platform": "安居客",
      "pref": "dislike",
      "rank": 14,
      "rent": 2300,
      "title": "张江租房帮转租32平一室一厅带阳台",
      "updated_at": "2026-07-01T13:20:49+00:00",
      "url": "https://sh.zu.anjuke.com/fangyuan/4636637714015242"
    },
    "https://sh.zu.anjuke.com/fangyuan/4636640108060675": {
      "area_m2": "39",
      "community": "芳华路63号小区",
      "layout": "1室1厅",
      "platform": "安居客",
      "pref": "dislike",
      "rank": 12,
      "rent": 2800,
      "title": "近地铁 交通便利 精装整租 押一付一 家电齐全 拎包入住",
      "updated_at": "2026-07-01T13:20:49+00:00",
      "url": "https://sh.zu.anjuke.com/fangyuan/4636640108060675"
    },
    "https://sh.zu.anjuke.com/fangyuan/4637047447413774": {
      "area_m2": "40",
      "community": "芳华路63号小区",
      "layout": "1室1厅",
      "platform": "安居客",
      "pref": "dislike",
      "rank": 13,
      "rent": 2800,
      "title": "冲鸭！近地铁 采光好 民用水电 免一个月租金 押一付一",
      "updated_at": "2026-07-01T13:20:49+00:00",
      "url": "https://sh.zu.anjuke.com/fangyuan/4637047447413774"
    },
    "https://sh.zu.anjuke.com/fangyuan/4637937880293383": {
      "area_m2": "45",
      "community": "川周公路2788弄小区",
      "layout": "1室1厅",
      "platform": "安居客",
      "pref": "dislike",
      "rank": 17,
      "rent": 2600,
      "title": "川周公路一室一厅，一厨一卫，全明户型。",
      "updated_at": "2026-07-01T13:20:49+00:00",
      "url": "https://sh.zu.anjuke.com/fangyuan/4637937880293383"
    },
    "https://sh.zu.anjuke.com/fangyuan/4639820402958336": {
      "area_m2": "39",
      "community": "川周公路2788弄小区",
      "layout": "1室1厅",
      "platform": "安居客",
      "pref": "dislike",
      "rank": 9,
      "rent": 2500,
      "title": "大平层带阳台 与大学生为伴 周边生活便利 押一付一没中介费",
      "updated_at": "2026-07-01T13:20:49+00:00",
      "url": "https://sh.zu.anjuke.com/fangyuan/4639820402958336"
    },
    "https://sh.zu.anjuke.com/fangyuan/4640545125571596": {
      "area_m2": "29",
      "community": "芳华路63号小区",
      "layout": "1室1厅",
      "platform": "安居客",
      "pref": "dislike",
      "rank": 30,
      "rent": 2800,
      "title": "夏日实惠一居室，长租月付，如果你是毕业生一定要看我",
      "updated_at": "2026-07-01T13:24:07+00:00",
      "url": "https://sh.zu.anjuke.com/fangyuan/4640545125571596"
    },
    "https://sh.zu.anjuke.com/fangyuan/4640712888034313": {
      "area_m2": "45",
      "community": "沪南路2420号楼",
      "layout": "1室1厅",
      "platform": "安居客",
      "pref": "dislike",
      "rank": 27,
      "rent": 2500,
      "title": "御桥前台管家在线出租，24小时服务及维修。安全省心",
      "updated_at": "2026-07-01T13:23:44+00:00",
      "url": "https://sh.zu.anjuke.com/fangyuan/4640712888034313"
    },
    "https://sh.zu.anjuke.com/fangyuan/4640808596267017": {
      "area_m2": "29.6",
      "community": "港城中环汇领寓",
      "layout": "1室0厅",
      "platform": "安居客",
      "pref": "dislike",
      "rank": 23,
      "rent": 2670,
      "title": "临张江近御桥靠商飞 国企保租房无费",
      "updated_at": "2026-07-01T13:22:21+00:00",
      "url": "https://sh.zu.anjuke.com/fangyuan/4640808596267017"
    },
    "https://sh.zu.anjuke.com/fangyuan/4640950734216198": {
      "area_m2": "60",
      "community": "沪南路2500号楼",
      "layout": "1室1厅",
      "platform": "安居客",
      "pref": "dislike",
      "rank": 31,
      "rent": 3000,
      "title": "急租管家 | 民用水电 | 带阳台 | 欢迎来电",
      "updated_at": "2026-07-01T13:24:10+00:00",
      "url": "https://sh.zu.anjuke.com/fangyuan/4640950734216198"
    },
    "https://sh.zu.anjuke.com/fangyuan/4641978409165829": {
      "area_m2": "35",
      "community": "川周公路2788弄小区",
      "layout": "1室1厅",
      "platform": "安居客",
      "pref": "dislike",
      "rank": 10,
      "rent": 2400,
      "title": "推窗见绿 帮张江转租ins风阳台小居",
      "updated_at": "2026-07-01T13:20:49+00:00",
      "url": "https://sh.zu.anjuke.com/fangyuan/4641978409165829"
    },
    "https://sh.zu.anjuke.com/fangyuan/4641987504513038": {
      "area_m2": "85",
      "community": "祝通苑",
      "layout": "2室2厅",
      "platform": "安居客",
      "pref": "like",
      "rank": 4,
      "rent": 2800,
      "title": "浦东机场 祝桥九院商飞附近祝通苑整租两室两厅民用水电拎包入住",
      "updated_at": "2026-07-01T13:20:49+00:00",
      "url": "https://sh.zu.anjuke.com/fangyuan/4641987504513038"
    },
    "https://sh.zu.anjuke.com/fangyuan/4642262079546373": {
      "area_m2": "31.3",
      "community": "港城中环汇领寓",
      "layout": "1室0厅",
      "platform": "安居客",
      "pref": "dislike",
      "rank": 22,
      "rent": 2770,
      "title": "上海梅雨季优先锁定 朝南独立阳台房",
      "updated_at": "2026-07-01T13:22:13+00:00",
      "url": "https://sh.zu.anjuke.com/fangyuan/4642262079546373"
    },
    "https://sh.zu.anjuke.com/fangyuan/4643255232355332": {
      "area_m2": "59.6",
      "community": "汤巷雅苑",
      "layout": "2室1厅",
      "platform": "安居客",
      "pref": "dislike",
      "rank": 20,
      "rent": 3600,
      "title": "近智元科技 近商务绿洲 双朝南 卫生间干湿分离 直达徐家汇",
      "updated_at": "2026-07-01T13:21:44+00:00",
      "url": "https://sh.zu.anjuke.com/fangyuan/4643255232355332"
    },
    "https://sh.zu.anjuke.com/fangyuan/4643362535644166": {
      "area_m2": "35",
      "community": "关岳路8弄5-6号小区",
      "layout": "1室1厅",
      "platform": "安居客",
      "pref": "dislike",
      "rank": 21,
      "rent": 2500,
      "title": "沪上优选近商圈地铁整租一房 南北通透 民水民电 拎包即住",
      "updated_at": "2026-07-01T13:22:05+00:00",
      "url": "https://sh.zu.anjuke.com/fangyuan/4643362535644166"
    },
    "https://sh.zu.anjuke.com/fangyuan/4643771125392390": {
      "area_m2": "75",
      "community": "城南路497弄小区",
      "layout": "2室1厅",
      "platform": "安居客",
      "pref": "dislike",
      "rank": 32,
      "rent": 3380,
      "title": "川沙地铁零距离城南路497弄小区，精装修南北通透，价格便宜",
      "updated_at": "2026-07-01T13:24:15+00:00",
      "url": "https://sh.zu.anjuke.com/fangyuan/4643771125392390"
    },
    "https://sh.zu.anjuke.com/fangyuan/4644711370923021": {
      "area_m2": "77.1",
      "community": "汇福家园兴盛里(北区)",
      "layout": "2室1厅",
      "platform": "安居客",
      "pref": "dislike",
      "rank": 38,
      "rent": 3500,
      "title": "近儿童医院，兴盛里两房出租民用水电，刚刚空，随时看房入住",
      "updated_at": "2026-07-01T13:24:55+00:00",
      "url": "https://sh.zu.anjuke.com/fangyuan/4644711370923021"
    },
    "https://sh.zu.anjuke.com/fangyuan/4644802221366286": {
      "area_m2": "31",
      "community": "川周公路2788弄小区",
      "layout": "1室1厅",
      "platform": "安居客",
      "pref": "dislike",
      "rank": 16,
      "rent": 2200,
      "title": "帮粉丝转租，11号线直达东体，YYDS",
      "updated_at": "2026-07-01T13:20:49+00:00",
      "url": "https://sh.zu.anjuke.com/fangyuan/4644802221366286"
    },
    "https://sh.zu.anjuke.com/gfangyuan/3830005373100040": {
      "area_m2": "70",
      "community": "川杨新苑(二期)",
      "layout": "2室1厅",
      "platform": "安居客",
      "pref": "dislike",
      "rank": 1,
      "rent": 3000,
      "title": "川杨新苑(二期) 2室1厅1卫",
      "updated_at": "2026-07-01T13:20:49+00:00",
      "url": "https://sh.zu.anjuke.com/gfangyuan/3830005373100040"
    },
    "https://sh.zu.anjuke.com/gfangyuan/4600580585708556": {
      "area_m2": "30",
      "community": "莲文苑",
      "layout": "1室1厅",
      "platform": "安居客",
      "pref": "dislike",
      "rank": 39,
      "rent": 2650,
      "title": "莲文苑 1室1厅1卫",
      "updated_at": "2026-07-01T13:25:01+00:00",
      "url": "https://sh.zu.anjuke.com/gfangyuan/4600580585708556"
    },
    "https://sh.zu.anjuke.com/gfangyuan/4638331771019279": {
      "area_m2": "57",
      "community": "由由四村",
      "layout": "2室1厅",
      "platform": "安居客",
      "pref": "dislike",
      "rank": 33,
      "rent": 3700,
      "title": "由由四村 2室1厅1卫",
      "updated_at": "2026-07-01T13:24:18+00:00",
      "url": "https://sh.zu.anjuke.com/gfangyuan/4638331771019279"
    },
    "https://sh.zu.anjuke.com/gfangyuan/4644023032306695": {
      "area_m2": "40",
      "community": "申城佳苑一期A块",
      "layout": "1室1厅",
      "platform": "安居客",
      "pref": "dislike",
      "rank": 40,
      "rent": 4000,
      "title": "申城佳苑一期A块 1室1厅1卫",
      "updated_at": "2026-07-01T13:25:05+00:00",
      "url": "https://sh.zu.anjuke.com/gfangyuan/4644023032306695"
    }
  },
  "updated_at": "2026-07-01T13:25:36+00:00",
  "version": 1
}
